EasyQuote/__init__.py
EasyQuote/main.py
EasyQuote-0.1.dist-info/METADATA
EasyQuote-0.1.dist-info/WHEEL
EasyQuote-0.1.dist-info/top_level.txt
EasyQuote-0.1.dist-info/RECORD
