Metadata-Version: 2.1
Name: EasyQuote
Version: 0.1
Requires-Dist: bs4
